limpapat/__init__.py
limpapat-0.0.6.dist-info/METADATA
limpapat-0.0.6.dist-info/WHEEL
limpapat-0.0.6.dist-info/top_level.txt
limpapat-0.0.6.dist-info/RECORD
