Metadata-Version: 2.1
Name: limpapat
Version: 0.0.6
Summary: A collection of my codes
Home-page: UNKNOWN
Author: Limpapat Bussaban
Author-email: lim.bussaban@gmail.com
License: UNKNOWN
Platform: UNKNOWN
Classifier: Programming Language :: Python :: 3
Classifier: License :: OSI Approved :: MIT License
Classifier: Operating System :: OS Independent
Requires-Python: >=3.6
Requires-Dist: torch
Requires-Dist: numpy
Requires-Dist: matplotlib
